pacmanupgradelist/__init__.py
pacmanupgradelist/cli.py
pacmanupgradelist-1.1.0.dist-info/LICENSE
pacmanupgradelist-1.1.0.dist-info/METADATA
pacmanupgradelist-1.1.0.dist-info/WHEEL
pacmanupgradelist-1.1.0.dist-info/entry_points.txt
pacmanupgradelist-1.1.0.dist-info/RECORD
